odoo/addons/shopinvader_multi_category/README.rst
odoo/addons/shopinvader_multi_category/__init__.py
odoo/addons/shopinvader_multi_category/__manifest__.py
odoo/addons/shopinvader_multi_category/i18n/shopinvader_multi_category.pot
odoo/addons/shopinvader_multi_category/models/__init__.py
odoo/addons/shopinvader_multi_category/models/shopinvader_product.py
odoo/addons/shopinvader_multi_category/readme/CONTRIBUTORS.rst
odoo/addons/shopinvader_multi_category/readme/CREDITS.rst
odoo/addons/shopinvader_multi_category/readme/DESCRIPTION.rst
odoo/addons/shopinvader_multi_category/readme/USAGE.rst
odoo/addons/shopinvader_multi_category/static/description/index.html
odoo/addons/shopinvader_multi_category/tests/__init__.py
odoo/addons/shopinvader_multi_category/tests/test_product.py
odoo12_addon_shopinvader_multi_category-12.0.1.0.0.99.dev4.dist-info/METADATA
odoo12_addon_shopinvader_multi_category-12.0.1.0.0.99.dev4.dist-info/WHEEL
odoo12_addon_shopinvader_multi_category-12.0.1.0.0.99.dev4.dist-info/top_level.txt
odoo12_addon_shopinvader_multi_category-12.0.1.0.0.99.dev4.dist-info/RECORD
